Modul_Shifr/Modul_Shifr.py
Modul_Shifr/__init__.py
shifr-0.0.1.dist-info/METADATA
shifr-0.0.1.dist-info/WHEEL
shifr-0.0.1.dist-info/top_level.txt
shifr-0.0.1.dist-info/RECORD
